ping_sweep/example_permissions.py
ping_sweep/ping_sweep.py
ping_sweep/__init__.py
ping_sweep/dpkt/ah.py
ping_sweep/dpkt/aim.py
ping_sweep/dpkt/arp.py
ping_sweep/dpkt/asn1.py
ping_sweep/dpkt/bgp.py
ping_sweep/dpkt/cdp.py
ping_sweep/dpkt/crc32c.py
ping_sweep/dpkt/dhcp.py
ping_sweep/dpkt/diameter.py
ping_sweep/dpkt/dns.py
ping_sweep/dpkt/dpkt.py
ping_sweep/dpkt/dtp.py
ping_sweep/dpkt/esp.py
ping_sweep/dpkt/ethernet.py
ping_sweep/dpkt/gre.py
ping_sweep/dpkt/gzip.py
ping_sweep/dpkt/h225.py
ping_sweep/dpkt/hsrp.py
ping_sweep/dpkt/http.py
ping_sweep/dpkt/icmp.py
ping_sweep/dpkt/icmp6.py
ping_sweep/dpkt/ieee80211.py
ping_sweep/dpkt/igmp.py
ping_sweep/dpkt/ip.py
ping_sweep/dpkt/ip6.py
ping_sweep/dpkt/ipx.py
ping_sweep/dpkt/llc.py
ping_sweep/dpkt/loopback.py
ping_sweep/dpkt/mrt.py
ping_sweep/dpkt/netbios.py
ping_sweep/dpkt/netflow.py
ping_sweep/dpkt/ntp.py
ping_sweep/dpkt/ospf.py
ping_sweep/dpkt/pcap.py
ping_sweep/dpkt/pim.py
ping_sweep/dpkt/pmap.py
ping_sweep/dpkt/ppp.py
ping_sweep/dpkt/pppoe.py
ping_sweep/dpkt/qq.py
ping_sweep/dpkt/radiotap.py
ping_sweep/dpkt/radius.py
ping_sweep/dpkt/rfb.py
ping_sweep/dpkt/rip.py
ping_sweep/dpkt/rpc.py
ping_sweep/dpkt/rtp.py
ping_sweep/dpkt/rx.py
ping_sweep/dpkt/sccp.py
ping_sweep/dpkt/sctp.py
ping_sweep/dpkt/sip.py
ping_sweep/dpkt/sll.py
ping_sweep/dpkt/smb.py
ping_sweep/dpkt/snoop.py
ping_sweep/dpkt/ssl.py
ping_sweep/dpkt/stp.py
ping_sweep/dpkt/stun.py
ping_sweep/dpkt/tcp.py
ping_sweep/dpkt/telnet.py
ping_sweep/dpkt/tftp.py
ping_sweep/dpkt/tns.py
ping_sweep/dpkt/tpkt.py
ping_sweep/dpkt/udp.py
ping_sweep/dpkt/vrrp.py
ping_sweep/dpkt/yahoo.py
ping_sweep/dpkt/__init__.py
ping_sweep/dpkt/examples/dhcprequest.py
ping_sweep/dpkt/examples/dnsping.py
ping_sweep/dpkt/examples/nbtping.py
ping_sweep/dpkt/examples/ping.py
ping_sweep/dpkt/examples/__init__.py
ping_sweep/dpkt/tests/test-perf.py
ping_sweep/dpkt/tests/test-perf2.py
ping_sweep/dpkt/tests/__init__.py
ping_sweep-1.0.1.dist-info/DESCRIPTION.rst
ping_sweep-1.0.1.dist-info/entry_points.txt
ping_sweep-1.0.1.dist-info/METADATA
ping_sweep-1.0.1.dist-info/pydist.json
ping_sweep-1.0.1.dist-info/RECORD
ping_sweep-1.0.1.dist-info/top_level.txt
ping_sweep-1.0.1.dist-info/WHEEL
