Metadata-Version: 2.0
Name: ping-sweep
Version: 1.0.1
Summary: Ping return time analysis tool
Home-page: https://github.com/Who8MyLunch/Ping_Sweep
Author: Pierre V. Villeneuve
Author-email: pierre.villeneuve@gmail.com
License: FreeBSD
Platform: UNKNOWN
